[
	{
		"text": "ა",
		"transcription": "a"
	},
	{
		"text": "ბ",
		"transcription": "b"
	},
	{
		"text": "გ",
		"transcription": "g"
	},
	{
		"text": "დ",
		"transcription": "d"
	},
	{
		"text": "ე",
		"transcription": "e"
	},
	{
		"text": "ვ",
		"transcription": "v"
	},
	{
		"text": "ზ",
		"transcription": "z"
	},
	{
		"text": "თ",
		"transcription": "t"
	},
	{
		"text": "ი",
		"transcription": "i"
	},
	{
		"text": "კ",
		"transcription": "k'"
	},
	{
		"text": "ლ",
		"transcription": "l"
	},
	{
		"text": "მ",
		"transcription": "m"
	},
	{
		"text": "ნ",
		"transcription": "n"
	},
	{
		"text": "ო",
		"transcription": "o"
	},
	{
		"text": "პ",
		"transcription": "p'"
	},
	{
		"text": "რ",
		"transcription": "r"
	},
	{
		"text": "ს",
		"transcription": "s"
	},
	{
		"text": "ტ",
		"transcription": "t'"
	},
	{
		"text": "უ",
		"transcription": "u"
	},
	{
		"text": "ფ",
		"transcription": "p"
	},
	{
		"text": "ქ",
		"transcription": "k"
	},
	{
		"text": "ღ",
		"transcription": "gh"
	},
	{
		"text": "ყ",
		"transcription": "q'"
	},
	{
		"text": "შ",
		"transcription": "sh"
	},
	{
		"text": "ჩ",
		"transcription": "ch"
	},
	{
		"text": "ც",
		"transcription": "ts"
	},
	{
		"text": "ძ",
		"transcription": "dz"
	},
	{
		"text": "წ",
		"transcription": "ts'"
	},
	{
		"text": "ჭ",
		"transcription": "ch'"
	},
	{
		"text": "ხ",
		"transcription": "kh"
	},
	{
		"text": "ჯ",
		"transcription": "j"
	},
	{
		"text": "ჰ",
		"transcription": "h"
	},
	{
		"text": "ჟ",
		"transcription": "zh"
	}
]
